[
    {
        "id": "0e6ea9b4-d5c2-441b-bf57-457982fd1522",
        "items": [
            {
                "dish_id": "e4b7f6a8-c23d-4e7a-b8f9-1c5d6a7e8b9c",
                "dish_name": "红烧肉",
                "quantity": 1,
                "price": 48,
                "total": 48,
                "image_path": "/static/images/dishes/df2b32d2-da54-450f-9b3e-e4b9bce8b6b5.jpg"
            },
            {
                "dish_id": "a1b2c3d4-e5f6-7a8b-9c0d-1e2f3a4b5c6d",
                "dish_name": "宫保鸡丁",
                "quantity": 1,
                "price": 38,
                "total": 38,
                "image_path": "/static/images/dishes/566b47f9-95f8-47f7-91b7-280e3cce6842.jpg"
            },
            {
                "dish_id": "d4e5f6a7-b8c9-d0e1-f2a3-b4c5d6e7f8a9",
                "dish_name": "蛋炒饭",
                "quantity": 1,
                "price": 22,
                "total": 22,
                "image_path": "/static/images/dishes/114abf84-0a43-47a9-bc45-bc4debe337c8.jpg"
            }
        ],
        "total_price": 108,
        "status": "completed",
        "timestamp": "2025-03-15T01:00:44.170911",
        "note": "要好吃",
        "updated_at": "2025-03-15T02:08:02.284813"
    },
    {
        "id": "aa1b7602-a778-47f4-b432-b57201312398",
        "items": [
            {
                "dish_id": "b2c3d4e5-f6a7-b8c9-d0e1-f2a3b4c5d6e7",
                "dish_name": "凉拌黄瓜",
                "quantity": 1,
                "price": 18,
                "total": 18,
                "image_path": "/static/images/dishes/4f530295-7fd5-4d80-b948-e43482287439.jpg"
            },
            {
                "dish_id": "c3d4e5f6-a7b8-c9d0-e1f2-a3b4c5d6e7f8",
                "dish_name": "蒜泥白肉",
                "quantity": 1,
                "price": 32,
                "total": 32,
                "image_path": "/static/images/dishes/d2d982b9-6e43-4c2b-b661-6c6986fe62b4.jpg"
            },
            {
                "dish_id": "e5f6a7b8-c9d0-e1f2-a3b4-c5d6e7f8a9b0",
                "dish_name": "番茄鸡蛋面",
                "quantity": 1,
                "price": 26,
                "total": 26,
                "image_path": "/static/images/dishes/3abc9645-9471-4e01-995a-fcdb1ec98c40.jpg"
            },
            {
                "dish_id": "d4e5f6a7-b8c9-d0e1-f2a3-b4c5d6e7f8a9",
                "dish_name": "蛋炒饭",
                "quantity": 1,
                "price": 22,
                "total": 22,
                "image_path": "/static/images/dishes/114abf84-0a43-47a9-bc45-bc4debe337c8.jpg"
            },
            {
                "dish_id": "f6a7b8c9-d0e1-f2a3-b4c5-d6e7f8a9b0c1",
                "dish_name": "柠檬水",
                "quantity": 1,
                "price": 12,
                "total": 12,
                "image_path": "/static/images/dishes/178ce3e9-4522-435d-8e91-23e02c239598.jpg"
            },
            {
                "dish_id": "a7b8c9d0-e1f2-a3b4-c5d6-e7f8a9b0c1d2",
                "dish_name": "美式咖啡",
                "quantity": 1,
                "price": 18,
                "total": 18,
                "image_path": "/static/images/dishes/733d54c2-2670-4c03-bc77-24447d7bb5bb.jpg"
            },
            {
                "dish_id": "c9d0e1f2-a3b4-c5d6-e7f8-a9b0c1d2e3f4",
                "dish_name": "提拉米苏",
                "quantity": 1,
                "price": 28,
                "total": 28,
                "image_path": "/static/images/dishes/88cda3ff-626c-4792-95ea-fc39d8b171b6.jpg"
            }
        ],
        "total_price": 156,
        "status": "completed",
        "timestamp": "2025-03-15T02:21:25.918777",
        "note": "好吃要",
        "updated_at": "2025-03-15T02:21:33.367139"
    },
    {
        "id": "daab0aa5-b65c-4ef6-aecc-fe393a8ce7a9",
        "items": [
            {
                "dish_id": "77095afd-d2f3-4f0a-8da8-452bf46c7727",
                "dish_name": "拿铁",
                "quantity": 1,
                "price": 8.0,
                "total": 8.0,
                "image_path": "/static/images/dishes/5545311f-0086-4b67-be01-796cae08b472.jpg"
            }
        ],
        "total_price": 8.0,
        "status": "completed",
        "timestamp": "2025-03-15T13:40:25.610162",
        "note": "",
        "updated_at": "2025-03-15T13:40:32.730782"
    }
]